swim/__init__.py
swim/__version__.py
swim/config.py
swim/main.py
swim/py.typed
swim/diagnostics/__init__.py
swim/diagnostics/health_checker.py
swim/diagnostics/message_tracer.py
swim/diagnostics/performance_analyzer.py
swim/events/__init__.py
swim/events/dispatcher.py
swim/events/handlers.py
swim/events/types.py
swim/integration/agent.py
swim/integration/load_balancer.py
swim/integration/message_router.py
swim/integration/messaging/ack_system.py
swim/integration/messaging/buffer_monitor.py
swim/integration/messaging/circuit_breaker.py
swim/integration/messaging/congestion.py
swim/integration/messaging/message_registry.py
swim/integration/messaging/reliability.py
swim/integration/messaging/trace.py
swim/integration/messaging/workflow.py
swim/integration/zmq/capacity_tracker.py
swim/integration/zmq/connection_manager.py
swim/integration/zmq/dealer.py
swim/integration/zmq/flow_control.py
swim/integration/zmq/monitoring.py
swim/integration/zmq/ordering.py
swim/integration/zmq/router.py
swim/lifeguard/__init__.py
swim/lifeguard/awareness.py
swim/lifeguard/probe_rate.py
swim/lifeguard/timing.py
swim/metrics/bandwidth.py
swim/metrics/collector.py
swim/metrics/latency.py
swim/metrics/metrics_cli.py
swim/metrics/api/__init__.py
swim/metrics/api/cli.py
swim/metrics/api/client.py
swim/metrics/api/integration.py
swim/metrics/api/server.py
swim/protocol/__init__.py
swim/protocol/disseminator.py
swim/protocol/failure_detector.py
swim/protocol/member.py
swim/protocol/message.py
swim/protocol/node.py
swim/protocol/sync.py
swim/transport/__init__.py
swim/transport/base.py
swim/transport/hybrid.py
swim/transport/tcp.py
swim/transport/udp.py
swim/utils/__init__.py
swim/utils/logging.py
swim/utils/network.py
swim/utils/rate_limiter.py
swim/utils/serialization.py
swim_p2p-1.2.5.dist-info/LICENSE
swim_p2p-1.2.5.dist-info/METADATA
swim_p2p-1.2.5.dist-info/WHEEL
swim_p2p-1.2.5.dist-info/entry_points.txt
swim_p2p-1.2.5.dist-info/top_level.txt
swim_p2p-1.2.5.dist-info/RECORD
