Metadata-Version: 2.1
Name: swim-p2p
Version: 1.2.5
Summary: SWIM Protocol implementation for P2P membership and failure detection with ZeroMQ integration
Author-email: Ruth Mutua <ruthmutua20@gmail.com>, Marriane Akeyo <annemarrieakeyo42@gmail.com>
Maintainer-email: Prescott Data <info@prescottdata.io>
License: MIT
Keywords: swim,p2p,distributed,membership,failure-detection,zeromq
Classifier: Development Status :: 3 - Alpha
Classifier: Intended Audience :: Developers
Classifier: Programming Language :: Python :: 3
Classifier: Programming Language :: Python :: 3.8
Classifier: Programming Language :: Python :: 3.9
Classifier: Programming Language :: Python :: 3.10
Classifier: Programming Language :: Python :: 3.11
Classifier: Programming Language :: Python :: 3.12
Classifier: Topic :: Software Development :: Libraries :: Python Modules
Classifier: Topic :: System :: Distributed Computing
Classifier: Topic :: System :: Networking
Requires-Python: >=3.8
License-File: LICENSE
Requires-Dist: pydantic>=2.0.0
Requires-Dist: pyzmq>=25.0.0
Requires-Dist: aiohttp>=3.8.0
Requires-Dist: psutil>=5.9.0
Provides-Extra: dev
Requires-Dist: pytest>=7.0.0; extra == "dev"
Requires-Dist: pytest-cov>=4.0.0; extra == "dev"
Requires-Dist: pytest-asyncio>=0.21.0; extra == "dev"
Provides-Extra: web
Requires-Dist: fastapi>=0.100.0; extra == "web"
Requires-Dist: uvicorn>=0.23.0; extra == "web"
